sci_parser/__init__.py
sci_parser/parser.py
sci_parser-0.1.1.dist-info/LICENSE
sci_parser-0.1.1.dist-info/METADATA
sci_parser-0.1.1.dist-info/WHEEL
sci_parser-0.1.1.dist-info/RECORD
